service_repository/__init__.py
service_repository/exceptions.py
service_repository/filters/__init__.py
service_repository/filters/exceptions.py
service_repository/filters/filters.py
service_repository/filters/models.py
service_repository/filters/pagination.py
service_repository/filters/sorting.py
service_repository/interfaces/__init__.py
service_repository/interfaces/repository.py
service_repository/interfaces/service.py
service_repository/repositories/__init__.py
service_repository/repositories/motor.py
service_repository/repositories/sqlalchemy.py
service_repository/services.py
service_repository-0.2.0.dist-info/LICENSE.md
service_repository-0.2.0.dist-info/WHEEL
service_repository-0.2.0.dist-info/METADATA
service_repository-0.2.0.dist-info/RECORD
